archive_mcp/__init__.py
archive_mcp/main.py
archive_mcp/utils/__init__.py
archive_mcp/utils/compression.py
archive_mcp-0.2.0.dist-info/METADATA
archive_mcp-0.2.0.dist-info/WHEEL
archive_mcp-0.2.0.dist-info/entry_points.txt
archive_mcp-0.2.0.dist-info/RECORD
