Metadata-Version: 2.4
Name: archive-mcp
Version: 0.2.0
Summary: A comprehensive MCP server for file compression and extraction operations
Requires-Python: >=3.10
Requires-Dist: mcp>=1.0.0
Requires-Dist: py7zr>=0.20.0
Requires-Dist: pydantic>=2.0.0
Requires-Dist: pyminizip>=0.2.6
Requires-Dist: pyzipper>=0.3.6
